Protoss_Probe, 4
Protoss_Pylon, 1
Protoss_Gateway, 1
Protoss_Probe, 4
Protoss_Zealot, 5
Protoss_Gateway, 1
Protoss_Zealot, 8
Protoss_Gateway, 1
Protoss_Cybernetics_Core, 1
Protoss_Zealot, 4
Protoss_Assimilator, 1
Protoss_Zealot, 10
Protoss_Dragoon, 3
Protoss_Robotics_Facility, 1
Protoss_Observatory, 1
Protoss_Observer, 1
Protoss_Probe, 3
Protoss_Protoss_Citadel_of_Adun, 1
Protoss_Zealot, 5
Protoss_Templar_Archives, 1
rotoss_Dark_Templar, 2
Protoss_Gateway, 1
Protoss_Zealot, 5
Protoss_Probe, 2
Protoss_Zealot, 6
Protoss_Probe, 3
Protoss_Dragoon, 3
Protoss_Zealot, 9
Protoss_Zealot, 4
Protoss_Dragoon, 2
Protoss_Observatory, 1
Protoss_Observer,1
Protoss_Gateway, 1
Protoss_Zealot, 4
Protoss_Dragoon, 2
Protoss_Zealot, 4
Protoss_Dragoon, 2
Protoss_Zealot, 4
Protoss_Dragoon, 2
Protoss_Zealot, 4
Protoss_Dragoon, 2
Protoss_Probe, 1
Protoss_Forge, 1
Protoss_Photon_Cannon, 3
Protoss_Zealot, 5
Protoss_Dragoon, 2
Protoss_Probe, 1
Protoss_Zealot, 5
Protoss_Gateway, 1
Protoss_Zealot, 5
Protoss_Photon_Cannon, 3
Protoss_Zealot, 5
Protoss_Zealot, 3
Protoss_Pylon, 1
Protoss_Pylon, 1
Protoss_Zealot, 4
Protoss_Pylon, 1
Protoss_Reaver, 1
Protoss_Probe, 1
Protoss_Zealot, 3
Protoss_Pylon, 1
Protoss_Gateway, 1
Protoss_Zealot, 6
Protoss_Probe, 1
Protoss_Pylon, 1
Protoss_Zealot, 3
default
Protoss_Pylon, 1
Protoss_Zealot, 6
emergency
Protoss_Zealot, 3
Protoss_Dragoon, 1
idle
Protoss_Zealot, 3
Protoss_Dragoon, 1